{"cameraMode":{"drawMode":0,"name":"Shaded","section":"Shading Mode"},"sceneLighting":true,"audioPlay":false,"sceneViewState":{"m_AlwaysRefresh":false,"showFog":true,"showSkybox":true,"showFlares":true,"showImageEffects":true,"showParticleSystems":true,"showVisualEffectGraphs":true,"m_FxEnabled":true},"in2DMode":false,"pivot":{"x":-11.084822654724121,"y":9.642696380615235,"z":0.7540596127510071},"rotation":{"x":0.2430628389120102,"y":0.6750995516777039,"z":-0.2535081207752228,"w":0.6489664316177368},"size":5.46984338760376,"orthographic":false}